hero/__init__.py
hero/hero.py
hero/inner/test_schema.json
hero_test-0.0.7.dist-info/WHEEL
hero_test-0.0.7.dist-info/METADATA
hero_test-0.0.7.dist-info/RECORD
